quantify_zurich_instruments/__init__.py
quantify_zurich_instruments/_static_version.py
quantify_zurich_instruments/_version.py
quantify_zurich_instruments/compilation.py
quantify_zurich_instruments/datastructures.py
quantify_zurich_instruments/gettable.py
quantify_zurich_instruments/helpers.py
quantify_zurich_instruments/instrument_coordinator.py
quantify_zurich_instruments/initialization_scripts/__init__.py
quantify_zurich_instruments/initialization_scripts/scqt_test_init.py
quantify_zurich_instruments/initialization_scripts/zi_setup.py
quantify_zurich_instruments-0.0.2.dist-info/licenses/LICENSE
quantify_zurich_instruments-0.0.2.dist-info/METADATA
quantify_zurich_instruments-0.0.2.dist-info/WHEEL
quantify_zurich_instruments-0.0.2.dist-info/top_level.txt
quantify_zurich_instruments-0.0.2.dist-info/RECORD
