Metadata-Version: 2.4
Name: quantify-zurich-instruments
Version: 0.0.2
Summary: Zurich Instruments backend for Quantify.
Author-email: Orange Quantum Systems <info@orangeqs.com>, Zurich Instruments Development Team <info@zhinst.com>
License: BSD 3-Clause License
Keywords: orange-quantum-systems,orangeqs,quantify,zurich-instruments,laboneq,quantum
Classifier: Development Status :: 4 - Beta
Classifier: Intended Audience :: Developers
Classifier: Intended Audience :: Science/Research
Classifier: License :: OSI Approved :: BSD License
Classifier: Natural Language :: English
Classifier: Programming Language :: Python :: 3
Classifier: Programming Language :: Python :: 3.9
Classifier: Programming Language :: Python :: 3.10
Classifier: Programming Language :: Python :: 3.11
Classifier: Programming Language :: Python :: 3.12
Classifier: Programming Language :: Python :: 3.13
Requires-Python: >=3.9
License-File: LICENSE
Requires-Dist: quantify_scheduler
Requires-Dist: laboneq
Requires-Dist: eval_type_backport
Requires-Dist: pydantic>=2.6
Provides-Extra: test
Requires-Dist: pytest; extra == "test"
Provides-Extra: docs
Requires-Dist: astroid<3.0; extra == "docs"
Requires-Dist: jupyter_sphinx>=0.4.0; extra == "docs"
Requires-Dist: jupytext; extra == "docs"
Requires-Dist: sphinx; extra == "docs"
Requires-Dist: pydata-sphinx-theme; extra == "docs"
Requires-Dist: myst-nb; extra == "docs"
Requires-Dist: hvplot; extra == "docs"
Requires-Dist: pylint; extra == "docs"
Requires-Dist: rich[jupyter]; extra == "docs"
Requires-Dist: scanpydoc; extra == "docs"
Requires-Dist: sphinx-autoapi; extra == "docs"
Requires-Dist: sphinx-autodoc-typehints; extra == "docs"
Requires-Dist: sphinx-design; extra == "docs"
Requires-Dist: sphinx-jsonschema; extra == "docs"
Requires-Dist: sphinx-togglebutton; extra == "docs"
Requires-Dist: sphinxcontrib-bibtex; extra == "docs"
Provides-Extra: dev
Requires-Dist: pytest; extra == "dev"
Requires-Dist: black; extra == "dev"
Requires-Dist: nbstripout; extra == "dev"
Requires-Dist: pre-commit; extra == "dev"
Requires-Dist: pyright; extra == "dev"
Requires-Dist: pytest-cov; extra == "dev"
Requires-Dist: pytest-xdist; extra == "dev"
Requires-Dist: ruff; extra == "dev"
Dynamic: license-file
